Calibration/__init__.py
Calibration/calibration.py
Calibration/calibration_utils.py
Calibration/utils_test.py
probability_calibration-0.0.1.dist-info/LICENSE
probability_calibration-0.0.1.dist-info/METADATA
probability_calibration-0.0.1.dist-info/WHEEL
probability_calibration-0.0.1.dist-info/top_level.txt
probability_calibration-0.0.1.dist-info/RECORD
