Metadata-Version: 2.1
Name: probability-calibration
Version: 0.0.1
Summary: Utilities to calibrate model outcome probability and evaluate calibration.
Home-page: https://github.com/Jooeys/ProbCalib2D
Author: Junyi Zhong
Author-email: jyzh@yahoo.com
License: UNKNOWN
Platform: UNKNOWN
Classifier: Programming Language :: Python :: 3
Classifier: License :: OSI Approved :: MIT License
Classifier: Operating System :: OS Independent
Requires-Python: >=3.6
Requires-Dist: numpy
Requires-Dist: sklearn
Requires-Dist: parameterized
